{"nodes": [{"id": "c_users_micr_trad_onedrive_desktop_new_folder_8_mediverify_src_routes_dashboard_qr_library_tsx", "label": "qr-library.tsx", "file_type": "code", "source_file": "C:\\Users\\MICR TRAD\\OneDrive\\Desktop\\New folder (8)\\Mediverify\\src\\routes\\dashboard\\qr-library.tsx", "source_location": "L1"}, {"id": "dashboard_qr_library_formatdate", "label": "formatDate()", "file_type": "code", "source_file": "C:\\Users\\MICR TRAD\\OneDrive\\Desktop\\New folder (8)\\Mediverify\\src\\routes\\dashboard\\qr-library.tsx", "source_location": "L37"}, {"id": "dashboard_qr_library_batchdetailpanel", "label": "BatchDetailPanel()", "file_type": "code", "source_file": "C:\\Users\\MICR TRAD\\OneDrive\\Desktop\\New folder (8)\\Mediverify\\src\\routes\\dashboard\\qr-library.tsx", "source_location": "L52"}, {"id": "dashboard_qr_library_cn", "label": "cn()", "file_type": "code", "source_file": "C:\\Users\\MICR TRAD\\OneDrive\\Desktop\\New folder (8)\\Mediverify\\src\\routes\\dashboard\\qr-library.tsx", "source_location": "L361"}], "edges": [{"source": "c_users_micr_trad_onedrive_desktop_new_folder_8_mediverify_src_routes_dashboard_qr_library_tsx", "target": "react_router", "relation": "imports_from", "confidence": "EXTRACTED", "source_file": "C:\\Users\\MICR TRAD\\OneDrive\\Desktop\\New folder (8)\\Mediverify\\src\\routes\\dashboard\\qr-library.tsx", "source_location": "L1", "weight": 1.0}, {"source": "c_users_micr_trad_onedrive_desktop_new_folder_8_mediverify_src_routes_dashboard_qr_library_tsx", "target": "react", "relation": "imports_from", "confidence": "EXTRACTED", "source_file": "C:\\Users\\MICR TRAD\\OneDrive\\Desktop\\New folder (8)\\Mediverify\\src\\routes\\dashboard\\qr-library.tsx", "source_location": "L2", "weight": 1.0}, {"source": "c_users_micr_trad_onedrive_desktop_new_folder_8_mediverify_src_routes_dashboard_qr_library_tsx", "target": "framer_motion", "relation": "imports_from", "confidence": "EXTRACTED", "source_file": "C:\\Users\\MICR TRAD\\OneDrive\\Desktop\\New folder (8)\\Mediverify\\src\\routes\\dashboard\\qr-library.tsx", "source_location": "L3", "weight": 1.0}, {"source": "c_users_micr_trad_onedrive_desktop_new_folder_8_mediverify_src_routes_dashboard_qr_library_tsx", "target": "lucide_react", "relation": "imports_from", "confidence": "EXTRACTED", "source_file": "C:\\Users\\MICR TRAD\\OneDrive\\Desktop\\New folder (8)\\Mediverify\\src\\routes\\dashboard\\qr-library.tsx", "source_location": "L4", "weight": 1.0}, {"source": "c_users_micr_trad_onedrive_desktop_new_folder_8_mediverify_src_routes_dashboard_qr_library_tsx", "target": "auth_context", "relation": "imports_from", "confidence": "EXTRACTED", "source_file": "C:\\Users\\MICR TRAD\\OneDrive\\Desktop\\New folder (8)\\Mediverify\\src\\routes\\dashboard\\qr-library.tsx", "source_location": "L10", "weight": 1.0}, {"source": "c_users_micr_trad_onedrive_desktop_new_folder_8_mediverify_src_routes_dashboard_qr_library_tsx", "target": "nav", "relation": "imports_from", "confidence": "EXTRACTED", "source_file": "C:\\Users\\MICR TRAD\\OneDrive\\Desktop\\New folder (8)\\Mediverify\\src\\routes\\dashboard\\qr-library.tsx", "source_location": "L11", "weight": 1.0}, {"source": "c_users_micr_trad_onedrive_desktop_new_folder_8_mediverify_src_routes_dashboard_qr_library_tsx", "target": "motion", "relation": "imports_from", "confidence": "EXTRACTED", "source_file": "C:\\Users\\MICR TRAD\\OneDrive\\Desktop\\New folder (8)\\Mediverify\\src\\routes\\dashboard\\qr-library.tsx", "source_location": "L12", "weight": 1.0}, {"source": "c_users_micr_trad_onedrive_desktop_new_folder_8_mediverify_src_routes_dashboard_qr_library_tsx", "target": "dashshell", "relation": "imports_from", "confidence": "EXTRACTED", "source_file": "C:\\Users\\MICR TRAD\\OneDrive\\Desktop\\New folder (8)\\Mediverify\\src\\routes\\dashboard\\qr-library.tsx", "source_location": "L13", "weight": 1.0}, {"source": "c_users_micr_trad_onedrive_desktop_new_folder_8_mediverify_src_routes_dashboard_qr_library_tsx", "target": "button", "relation": "imports_from", "confidence": "EXTRACTED", "source_file": "C:\\Users\\MICR TRAD\\OneDrive\\Desktop\\New folder (8)\\Mediverify\\src\\routes\\dashboard\\qr-library.tsx", "source_location": "L14", "weight": 1.0}, {"source": "c_users_micr_trad_onedrive_desktop_new_folder_8_mediverify_src_routes_dashboard_qr_library_tsx", "target": "input", "relation": "imports_from", "confidence": "EXTRACTED", "source_file": "C:\\Users\\MICR TRAD\\OneDrive\\Desktop\\New folder (8)\\Mediverify\\src\\routes\\dashboard\\qr-library.tsx", "source_location": "L15", "weight": 1.0}, {"source": "c_users_micr_trad_onedrive_desktop_new_folder_8_mediverify_src_routes_dashboard_qr_library_tsx", "target": "qr_store", "relation": "imports_from", "confidence": "EXTRACTED", "source_file": "C:\\Users\\MICR TRAD\\OneDrive\\Desktop\\New folder (8)\\Mediverify\\src\\routes\\dashboard\\qr-library.tsx", "source_location": "L16", "weight": 1.0}, {"source": "c_users_micr_trad_onedrive_desktop_new_folder_8_mediverify_src_routes_dashboard_qr_library_tsx", "target": "dual_qr", "relation": "imports_from", "confidence": "EXTRACTED", "source_file": "C:\\Users\\MICR TRAD\\OneDrive\\Desktop\\New folder (8)\\Mediverify\\src\\routes\\dashboard\\qr-library.tsx", "source_location": "L17", "weight": 1.0}, {"source": "c_users_micr_trad_onedrive_desktop_new_folder_8_mediverify_src_routes_dashboard_qr_library_tsx", "target": "qrcode_react", "relation": "imports_from", "confidence": "EXTRACTED", "source_file": "C:\\Users\\MICR TRAD\\OneDrive\\Desktop\\New folder (8)\\Mediverify\\src\\routes\\dashboard\\qr-library.tsx", "source_location": "L18", "weight": 1.0}, {"source": "c_users_micr_trad_onedrive_desktop_new_folder_8_mediverify_src_routes_dashboard_qr_library_tsx", "target": "qrcode", "relation": "imports_from", "confidence": "EXTRACTED", "source_file": "C:\\Users\\MICR TRAD\\OneDrive\\Desktop\\New folder (8)\\Mediverify\\src\\routes\\dashboard\\qr-library.tsx", "source_location": "L19", "weight": 1.0}, {"source": "c_users_micr_trad_onedrive_desktop_new_folder_8_mediverify_src_routes_dashboard_qr_library_tsx", "target": "printing_service", "relation": "imports_from", "confidence": "EXTRACTED", "source_file": "C:\\Users\\MICR TRAD\\OneDrive\\Desktop\\New folder (8)\\Mediverify\\src\\routes\\dashboard\\qr-library.tsx", "source_location": "L20", "weight": 1.0}, {"source": "c_users_micr_trad_onedrive_desktop_new_folder_8_mediverify_src_routes_dashboard_qr_library_tsx", "target": "file_saver", "relation": "imports_from", "confidence": "EXTRACTED", "source_file": "C:\\Users\\MICR TRAD\\OneDrive\\Desktop\\New folder (8)\\Mediverify\\src\\routes\\dashboard\\qr-library.tsx", "source_location": "L21", "weight": 1.0}, {"source": "c_users_micr_trad_onedrive_desktop_new_folder_8_mediverify_src_routes_dashboard_qr_library_tsx", "target": "sonner", "relation": "imports_from", "confidence": "EXTRACTED", "source_file": "C:\\Users\\MICR TRAD\\OneDrive\\Desktop\\New folder (8)\\Mediverify\\src\\routes\\dashboard\\qr-library.tsx", "source_location": "L22", "weight": 1.0}, {"source": "c_users_micr_trad_onedrive_desktop_new_folder_8_mediverify_src_routes_dashboard_qr_library_tsx", "target": "utils", "relation": "imports_from", "confidence": "EXTRACTED", "source_file": "C:\\Users\\MICR TRAD\\OneDrive\\Desktop\\New folder (8)\\Mediverify\\src\\routes\\dashboard\\qr-library.tsx", "source_location": "L23", "weight": 1.0}, {"source": "c_users_micr_trad_onedrive_desktop_new_folder_8_mediverify_src_routes_dashboard_qr_library_tsx", "target": "dashboard_qr_library_formatdate", "relation": "contains", "confidence": "EXTRACTED", "source_file": "C:\\Users\\MICR TRAD\\OneDrive\\Desktop\\New folder (8)\\Mediverify\\src\\routes\\dashboard\\qr-library.tsx", "source_location": "L37", "weight": 1.0}, {"source": "c_users_micr_trad_onedrive_desktop_new_folder_8_mediverify_src_routes_dashboard_qr_library_tsx", "target": "dashboard_qr_library_batchdetailpanel", "relation": "contains", "confidence": "EXTRACTED", "source_file": "C:\\Users\\MICR TRAD\\OneDrive\\Desktop\\New folder (8)\\Mediverify\\src\\routes\\dashboard\\qr-library.tsx", "source_location": "L52", "weight": 1.0}, {"source": "c_users_micr_trad_onedrive_desktop_new_folder_8_mediverify_src_routes_dashboard_qr_library_tsx", "target": "dashboard_qr_library_cn", "relation": "contains", "confidence": "EXTRACTED", "source_file": "C:\\Users\\MICR TRAD\\OneDrive\\Desktop\\New folder (8)\\Mediverify\\src\\routes\\dashboard\\qr-library.tsx", "source_location": "L361", "weight": 1.0}, {"source": "c_users_micr_trad_onedrive_desktop_new_folder_8_mediverify_src_routes_dashboard_qr_library_tsx", "target": "dashboard_qr_library_cn", "relation": "contains", "confidence": "EXTRACTED", "source_file": "C:\\Users\\MICR TRAD\\OneDrive\\Desktop\\New folder (8)\\Mediverify\\src\\routes\\dashboard\\qr-library.tsx", "source_location": "L556", "weight": 1.0}], "raw_calls": [{"caller_nid": "dashboard_qr_library_formatdate", "callee": "isNaN", "source_file": "C:\\Users\\MICR TRAD\\OneDrive\\Desktop\\New folder (8)\\Mediverify\\src\\routes\\dashboard\\qr-library.tsx", "source_location": "L40"}, {"caller_nid": "dashboard_qr_library_formatdate", "callee": "getTime", "source_file": "C:\\Users\\MICR TRAD\\OneDrive\\Desktop\\New folder (8)\\Mediverify\\src\\routes\\dashboard\\qr-library.tsx", "source_location": "L40"}, {"caller_nid": "dashboard_qr_library_formatdate", "callee": "toLocaleDateString", "source_file": "C:\\Users\\MICR TRAD\\OneDrive\\Desktop\\New folder (8)\\Mediverify\\src\\routes\\dashboard\\qr-library.tsx", "source_location": "L41"}, {"caller_nid": "dashboard_qr_library_batchdetailpanel", "callee": "useAuth", "source_file": "C:\\Users\\MICR TRAD\\OneDrive\\Desktop\\New folder (8)\\Mediverify\\src\\routes\\dashboard\\qr-library.tsx", "source_location": "L59"}, {"caller_nid": "dashboard_qr_library_batchdetailpanel", "callee": "useState", "source_file": "C:\\Users\\MICR TRAD\\OneDrive\\Desktop\\New folder (8)\\Mediverify\\src\\routes\\dashboard\\qr-library.tsx", "source_location": "L60"}, {"caller_nid": "dashboard_qr_library_batchdetailpanel", "callee": "useState", "source_file": "C:\\Users\\MICR TRAD\\OneDrive\\Desktop\\New folder (8)\\Mediverify\\src\\routes\\dashboard\\qr-library.tsx", "source_location": "L61"}, {"caller_nid": "dashboard_qr_library_batchdetailpanel", "callee": "useState", "source_file": "C:\\Users\\MICR TRAD\\OneDrive\\Desktop\\New folder (8)\\Mediverify\\src\\routes\\dashboard\\qr-library.tsx", "source_location": "L62"}, {"caller_nid": "dashboard_qr_library_batchdetailpanel", "callee": "useState", "source_file": "C:\\Users\\MICR TRAD\\OneDrive\\Desktop\\New folder (8)\\Mediverify\\src\\routes\\dashboard\\qr-library.tsx", "source_location": "L63"}, {"caller_nid": "dashboard_qr_library_batchdetailpanel", "callee": "useRef", "source_file": "C:\\Users\\MICR TRAD\\OneDrive\\Desktop\\New folder (8)\\Mediverify\\src\\routes\\dashboard\\qr-library.tsx", "source_location": "L65"}, {"caller_nid": "dashboard_qr_library_batchdetailpanel", "callee": "useRef", "source_file": "C:\\Users\\MICR TRAD\\OneDrive\\Desktop\\New folder (8)\\Mediverify\\src\\routes\\dashboard\\qr-library.tsx", "source_location": "L66"}, {"caller_nid": "dashboard_qr_library_batchdetailpanel", "callee": "useEffect", "source_file": "C:\\Users\\MICR TRAD\\OneDrive\\Desktop\\New folder (8)\\Mediverify\\src\\routes\\dashboard\\qr-library.tsx", "source_location": "L70"}]}